eidos_cli/__init__.py
eidos_cli/client.py
eidos_cli/main.py
eidos_cli/schema.py
eidos_cli/terminal.py
eidos_cli/util.py
eidos_cli-0.1.2.dist-info/METADATA
eidos_cli-0.1.2.dist-info/WHEEL
eidos_cli-0.1.2.dist-info/entry_points.txt
eidos_cli-0.1.2.dist-info/RECORD
