Metadata-Version: 2.1
Name: eidos-cli
Version: 0.1.2
Summary: 
Author: Luke Lalor
Author-email: lukehlalor@gmail.com
Requires-Python: >=3.11,<4.0
Classifier: Programming Language :: Python :: 3
Classifier: Programming Language :: Python :: 3.11
Classifier: Programming Language :: Python :: 3.12
Requires-Dist: cmd2 (>=2.4.3,<3.0.0)
Requires-Dist: httpx (>=0.25.2,<0.26.0)
Requires-Dist: rich (>=13.7.0,<14.0.0)
